air_quality_cli/__init__.py
air_quality_cli/app.py
air_quality_cli/constants.py
air_quality_cli/utils.py
air_quality_cli/commands/__init__.py
air_quality_cli/commands/add.py
air_quality_cli/commands/init.py
air_quality_cli/commands/search.py
air_quality_cli/commands/show.py
air_quality_cli-0.0.4.dist-info/LICENSE
air_quality_cli-0.0.4.dist-info/METADATA
air_quality_cli-0.0.4.dist-info/WHEEL
air_quality_cli-0.0.4.dist-info/entry_points.txt
air_quality_cli-0.0.4.dist-info/top_level.txt
air_quality_cli-0.0.4.dist-info/RECORD
