Metadata-Version: 2.1
Name: air-quality-cli
Version: 0.0.4
Summary: Get Air Quality Index from your CLI
Home-page: https://github.com/yankeexe/air-quality-cli
Author: Yankee Maharjan
License: MIT
Platform: UNKNOWN
Classifier: Programming Language :: Python :: 3.6
Classifier: Programming Language :: Python :: 3.7
Classifier: Programming Language :: Python :: 3.8
Classifier: Operating System :: OS Independent
Classifier: Development Status :: 4 - Beta
Classifier: License :: OSI Approved :: MIT License
Requires-Dist: click
Requires-Dist: requests
Requires-Dist: rich (<=7.1.0)
Requires-Dist: simple-term-menu
